{
  "CleanUpType": 0,
  "Steps": [
    {
      "StepType": 5,
      "ProceedType": 0,
      "DollTargetType": 0,
      "TargetDollOrientation": 0,
      "ExpressionType": 0,
      "DollPositionType": 0,
      "AnimationType": 0,
      "SubCutsceneType": 0,
      "NotificationType": 0,
      "GirlPairRelationshipType": 0,
      "SpecialStepPrefabName": null,
      "BannerTextPrefabName": null,
      "WindowPrefabName": null,
      "EmitterBehaviorName": null,
      "StringValue": "",
      "FloatValue": 0.0,
      "ProceedFloat": 0.0,
      "TargetGirlDefinitionID": 4,
      "IntValue": 0,
      "EaseType": 0,
      "EditorSelectedBranchIndex": 0,
      "DialogTriggerDefinitionID": -1,
      "EditorSelectedOptionIndex": 0,
      "GirlDefinitionID": -1,
      "ExpressionIndex": 0,
      "HairstyleIndex": 0,
      "OutfitIndex": 0,
      "SubCutsceneDefinitionID": -1,
      "SkipStep": false,
      "TargetAlt": false,
      "BoolValue": false,
      "SetMood": false,
      "ProceedBool": false,
      "PositionInfo": {
        "Xpos": 0.0,
        "Ypos": 0.0
      },
      "AudioKlipInfo": {
        "AudioClipInfo": null,
        "Volume": 1.0
      },
      "LogicActionInfo": {
        "Type": 0,
        "AffectionType": 0,
        "ResourceType": 0,
        "PuzzleState": 0,
        "StringValue": "",
        "FloatValue": 0.0,
        "IntValue": 0,
        "LocationDefinitionID": -1,
        "GirlPairDefinitionID": -1,
        "CutsceneDefinitionID": -1,
        "ItemDefinitionID": -1,
        "GirlDefinitionID": -1,
        "BoolValue": false,
        "BackgroundMusic": {
          "AudioClipInfo": null,
          "Volume": 1.0
        }
      },
      "DialogLineInfo": {
        "DialogText": "Polly,▸▸▸▸▸▸▸ your smile...▸▸▸▸▸ it's quite beautiful...▸▸▸▸▸ and yet...▸▸▸▸▸ it masks a dark truth...",
        "YuriDialogText": "",
        "Yuri": false,
        "YuriAudioClipInfo": null,
        "AudioClipInfo": {
          "Path": "vo_attr_zoey_polly_1_zoey",
          "IsExternal": false
        },
        "StartExpression": {
          "expressionType": 0,
          "eyesClosed": false,
          "percentRead": 0.0
        },
        "EndExpression": {
          "expressionType": 7,
          "eyesClosed": false,
          "percentRead": 0.0
        },
        "Expressions": [
          {
            "expressionType": 7,
            "eyesClosed": false,
            "percentRead": 0.581818163
          }
        ]
      },
      "DialogOptionInfos": [],
      "BranchInfos": []
    },
    {
      "StepType": 5,
      "ProceedType": 0,
      "DollTargetType": 0,
      "TargetDollOrientation": 0,
      "ExpressionType": 0,
      "DollPositionType": 0,
      "AnimationType": 0,
      "SubCutsceneType": 0,
      "NotificationType": 0,
      "GirlPairRelationshipType": 0,
      "SpecialStepPrefabName": null,
      "BannerTextPrefabName": null,
      "WindowPrefabName": null,
      "EmitterBehaviorName": null,
      "StringValue": "",
      "FloatValue": 0.0,
      "ProceedFloat": 0.0,
      "TargetGirlDefinitionID": 12,
      "IntValue": 0,
      "EaseType": 0,
      "EditorSelectedBranchIndex": 0,
      "DialogTriggerDefinitionID": -1,
      "EditorSelectedOptionIndex": 0,
      "GirlDefinitionID": -1,
      "ExpressionIndex": 0,
      "HairstyleIndex": 0,
      "OutfitIndex": 0,
      "SubCutsceneDefinitionID": -1,
      "SkipStep": false,
      "TargetAlt": false,
      "BoolValue": false,
      "SetMood": false,
      "ProceedBool": false,
      "PositionInfo": {
        "Xpos": 0.0,
        "Ypos": 0.0
      },
      "AudioKlipInfo": {
        "AudioClipInfo": null,
        "Volume": 1.0
      },
      "LogicActionInfo": {
        "Type": 0,
        "AffectionType": 0,
        "ResourceType": 0,
        "PuzzleState": 0,
        "StringValue": "",
        "FloatValue": 0.0,
        "IntValue": 0,
        "LocationDefinitionID": -1,
        "GirlPairDefinitionID": -1,
        "CutsceneDefinitionID": -1,
        "ItemDefinitionID": -1,
        "GirlDefinitionID": -1,
        "BoolValue": false,
        "BackgroundMusic": {
          "AudioClipInfo": null,
          "Volume": 1.0
        }
      },
      "DialogLineInfo": {
        "DialogText": "W-▸▸▸what?[h]",
        "YuriDialogText": "",
        "Yuri": false,
        "YuriAudioClipInfo": null,
        "AudioClipInfo": {
          "Path": "vo_attr_zoey_polly_2_polly",
          "IsExternal": false
        },
        "StartExpression": {
          "expressionType": 4,
          "eyesClosed": false,
          "percentRead": 0.0
        },
        "EndExpression": {
          "expressionType": 4,
          "eyesClosed": false,
          "percentRead": 0.0
        },
        "Expressions": []
      },
      "DialogOptionInfos": [],
      "BranchInfos": []
    },
    {
      "StepType": 5,
      "ProceedType": 0,
      "DollTargetType": 0,
      "TargetDollOrientation": 0,
      "ExpressionType": 0,
      "DollPositionType": 0,
      "AnimationType": 0,
      "SubCutsceneType": 0,
      "NotificationType": 0,
      "GirlPairRelationshipType": 0,
      "SpecialStepPrefabName": null,
      "BannerTextPrefabName": null,
      "WindowPrefabName": null,
      "EmitterBehaviorName": null,
      "StringValue": "",
      "FloatValue": 0.0,
      "ProceedFloat": 0.0,
      "TargetGirlDefinitionID": 4,
      "IntValue": 0,
      "EaseType": 0,
      "EditorSelectedBranchIndex": 0,
      "DialogTriggerDefinitionID": -1,
      "EditorSelectedOptionIndex": 0,
      "GirlDefinitionID": -1,
      "ExpressionIndex": 0,
      "HairstyleIndex": 0,
      "OutfitIndex": 0,
      "SubCutsceneDefinitionID": -1,
      "SkipStep": false,
      "TargetAlt": false,
      "BoolValue": false,
      "SetMood": false,
      "ProceedBool": false,
      "PositionInfo": {
        "Xpos": 0.0,
        "Ypos": 0.0
      },
      "AudioKlipInfo": {
        "AudioClipInfo": null,
        "Volume": 1.0
      },
      "LogicActionInfo": {
        "Type": 0,
        "AffectionType": 0,
        "ResourceType": 0,
        "PuzzleState": 0,
        "StringValue": "",
        "FloatValue": 0.0,
        "IntValue": 0,
        "LocationDefinitionID": -1,
        "GirlPairDefinitionID": -1,
        "CutsceneDefinitionID": -1,
        "ItemDefinitionID": -1,
        "GirlDefinitionID": -1,
        "BoolValue": false,
        "BackgroundMusic": {
          "AudioClipInfo": null,
          "Volume": 1.0
        }
      },
      "DialogLineInfo": {
        "DialogText": "I sense a lot of pain,▸▸▸▸▸ from your past...▸▸▸▸▸▸▸▸▸▸ pain that's with you still today,▸▸▸▸▸ is it not?",
        "YuriDialogText": "",
        "Yuri": false,
        "YuriAudioClipInfo": null,
        "AudioClipInfo": {
          "Path": "vo_attr_zoey_polly_3_zoey",
          "IsExternal": false
        },
        "StartExpression": {
          "expressionType": 7,
          "eyesClosed": true,
          "percentRead": 0.0
        },
        "EndExpression": {
          "expressionType": 0,
          "eyesClosed": false,
          "percentRead": 0.0
        },
        "Expressions": [
          {
            "expressionType": 7,
            "eyesClosed": false,
            "percentRead": 0.272727281
          },
          {
            "expressionType": 0,
            "eyesClosed": false,
            "percentRead": 0.5181818
          }
        ]
      },
      "DialogOptionInfos": [],
      "BranchInfos": []
    },
    {
      "StepType": 5,
      "ProceedType": 0,
      "DollTargetType": 0,
      "TargetDollOrientation": 0,
      "ExpressionType": 0,
      "DollPositionType": 0,
      "AnimationType": 0,
      "SubCutsceneType": 0,
      "NotificationType": 0,
      "GirlPairRelationshipType": 0,
      "SpecialStepPrefabName": null,
      "BannerTextPrefabName": null,
      "WindowPrefabName": null,
      "EmitterBehaviorName": null,
      "StringValue": "",
      "FloatValue": 0.0,
      "ProceedFloat": 0.0,
      "TargetGirlDefinitionID": 12,
      "IntValue": 0,
      "EaseType": 0,
      "EditorSelectedBranchIndex": 0,
      "DialogTriggerDefinitionID": -1,
      "EditorSelectedOptionIndex": 0,
      "GirlDefinitionID": -1,
      "ExpressionIndex": 0,
      "HairstyleIndex": 0,
      "OutfitIndex": 0,
      "SubCutsceneDefinitionID": -1,
      "SkipStep": false,
      "TargetAlt": false,
      "BoolValue": false,
      "SetMood": false,
      "ProceedBool": false,
      "PositionInfo": {
        "Xpos": 0.0,
        "Ypos": 0.0
      },
      "AudioKlipInfo": {
        "AudioClipInfo": null,
        "Volume": 1.0
      },
      "LogicActionInfo": {
        "Type": 0,
        "AffectionType": 0,
        "ResourceType": 0,
        "PuzzleState": 0,
        "StringValue": "",
        "FloatValue": 0.0,
        "IntValue": 0,
        "LocationDefinitionID": -1,
        "GirlPairDefinitionID": -1,
        "CutsceneDefinitionID": -1,
        "ItemDefinitionID": -1,
        "GirlDefinitionID": -1,
        "BoolValue": false,
        "BackgroundMusic": {
          "AudioClipInfo": null,
          "Volume": 1.0
        }
      },
      "DialogLineInfo": {
        "DialogText": "Y[y]-▸▸▸▸▸y[y]eah...[hh]▸▸▸▸▸▸▸▸▸▸▸▸▸ I don't...▸▸▸▸▸▸▸▸ how do you know about that?",
        "YuriDialogText": "",
        "Yuri": false,
        "YuriAudioClipInfo": null,
        "AudioClipInfo": {
          "Path": "vo_attr_zoey_polly_4_polly",
          "IsExternal": false
        },
        "StartExpression": {
          "expressionType": 2,
          "eyesClosed": false,
          "percentRead": 0.0
        },
        "EndExpression": {
          "expressionType": 4,
          "eyesClosed": false,
          "percentRead": 0.0
        },
        "Expressions": [
          {
            "expressionType": 4,
            "eyesClosed": false,
            "percentRead": 0.6181818
          }
        ]
      },
      "DialogOptionInfos": [],
      "BranchInfos": []
    },
    {
      "StepType": 5,
      "ProceedType": 0,
      "DollTargetType": 0,
      "TargetDollOrientation": 0,
      "ExpressionType": 0,
      "DollPositionType": 0,
      "AnimationType": 0,
      "SubCutsceneType": 0,
      "NotificationType": 0,
      "GirlPairRelationshipType": 0,
      "SpecialStepPrefabName": null,
      "BannerTextPrefabName": null,
      "WindowPrefabName": null,
      "EmitterBehaviorName": null,
      "StringValue": "",
      "FloatValue": 0.0,
      "ProceedFloat": 0.0,
      "TargetGirlDefinitionID": 4,
      "IntValue": 0,
      "EaseType": 0,
      "EditorSelectedBranchIndex": 0,
      "DialogTriggerDefinitionID": -1,
      "EditorSelectedOptionIndex": 0,
      "GirlDefinitionID": -1,
      "ExpressionIndex": 0,
      "HairstyleIndex": 0,
      "OutfitIndex": 0,
      "SubCutsceneDefinitionID": -1,
      "SkipStep": false,
      "TargetAlt": false,
      "BoolValue": false,
      "SetMood": false,
      "ProceedBool": false,
      "PositionInfo": {
        "Xpos": 0.0,
        "Ypos": 0.0
      },
      "AudioKlipInfo": {
        "AudioClipInfo": null,
        "Volume": 1.0
      },
      "LogicActionInfo": {
        "Type": 0,
        "AffectionType": 0,
        "ResourceType": 0,
        "PuzzleState": 0,
        "StringValue": "",
        "FloatValue": 0.0,
        "IntValue": 0,
        "LocationDefinitionID": -1,
        "GirlPairDefinitionID": -1,
        "CutsceneDefinitionID": -1,
        "ItemDefinitionID": -1,
        "GirlDefinitionID": -1,
        "BoolValue": false,
        "BackgroundMusic": {
          "AudioClipInfo": null,
          "Volume": 1.0
        }
      },
      "DialogLineInfo": {
        "DialogText": "I have certain...▸▸▸▸▸▸▸ intuitions,▸▸▸▸▸[s]▸▸▸▸▸ about people.",
        "YuriDialogText": "",
        "Yuri": false,
        "YuriAudioClipInfo": null,
        "AudioClipInfo": {
          "Path": "vo_attr_zoey_polly_5_zoey",
          "IsExternal": false
        },
        "StartExpression": {
          "expressionType": 0,
          "eyesClosed": false,
          "percentRead": 0.0
        },
        "EndExpression": {
          "expressionType": 0,
          "eyesClosed": false,
          "percentRead": 0.0
        },
        "Expressions": [
          {
            "expressionType": 7,
            "eyesClosed": false,
            "percentRead": 0.4
          },
          {
            "expressionType": 0,
            "eyesClosed": false,
            "percentRead": 0.763636351
          }
        ]
      },
      "DialogOptionInfos": [],
      "BranchInfos": []
    },
    {
      "StepType": 5,
      "ProceedType": 0,
      "DollTargetType": 0,
      "TargetDollOrientation": 0,
      "ExpressionType": 0,
      "DollPositionType": 0,
      "AnimationType": 0,
      "SubCutsceneType": 0,
      "NotificationType": 0,
      "GirlPairRelationshipType": 0,
      "SpecialStepPrefabName": null,
      "BannerTextPrefabName": null,
      "WindowPrefabName": null,
      "EmitterBehaviorName": null,
      "StringValue": "",
      "FloatValue": 0.0,
      "ProceedFloat": 0.0,
      "TargetGirlDefinitionID": 12,
      "IntValue": 0,
      "EaseType": 0,
      "EditorSelectedBranchIndex": 0,
      "DialogTriggerDefinitionID": -1,
      "EditorSelectedOptionIndex": 0,
      "GirlDefinitionID": -1,
      "ExpressionIndex": 0,
      "HairstyleIndex": 0,
      "OutfitIndex": 0,
      "SubCutsceneDefinitionID": -1,
      "SkipStep": false,
      "TargetAlt": false,
      "BoolValue": false,
      "SetMood": false,
      "ProceedBool": false,
      "PositionInfo": {
        "Xpos": 0.0,
        "Ypos": 0.0
      },
      "AudioKlipInfo": {
        "AudioClipInfo": null,
        "Volume": 1.0
      },
      "LogicActionInfo": {
        "Type": 0,
        "AffectionType": 0,
        "ResourceType": 0,
        "PuzzleState": 0,
        "StringValue": "",
        "FloatValue": 0.0,
        "IntValue": 0,
        "LocationDefinitionID": -1,
        "GirlPairDefinitionID": -1,
        "CutsceneDefinitionID": -1,
        "ItemDefinitionID": -1,
        "GirlDefinitionID": -1,
        "BoolValue": false,
        "BackgroundMusic": {
          "AudioClipInfo": null,
          "Volume": 1.0
        }
      },
      "DialogLineInfo": {
        "DialogText": "It...▸▸▸▸▸▸▸ wasn't always easy,▸▸ growin' up.▸▸▸▸▸▸▸▸▸▸ I got bullied a lot.▸▸▸▸▸ People just...▸▸▸▸▸ didn't▸▸ understand▸▸ me.",
        "YuriDialogText": "",
        "Yuri": false,
        "YuriAudioClipInfo": null,
        "AudioClipInfo": {
          "Path": "vo_attr_zoey_polly_6_polly",
          "IsExternal": false
        },
        "StartExpression": {
          "expressionType": 2,
          "eyesClosed": false,
          "percentRead": 0.0
        },
        "EndExpression": {
          "expressionType": 2,
          "eyesClosed": false,
          "percentRead": 0.0
        },
        "Expressions": [
          {
            "expressionType": 2,
            "eyesClosed": true,
            "percentRead": 0.427272737
          },
          {
            "expressionType": 4,
            "eyesClosed": false,
            "percentRead": 0.6272727
          },
          {
            "expressionType": 2,
            "eyesClosed": false,
            "percentRead": 0.7818182
          }
        ]
      },
      "DialogOptionInfos": [],
      "BranchInfos": []
    },
    {
      "StepType": 5,
      "ProceedType": 0,
      "DollTargetType": 0,
      "TargetDollOrientation": 0,
      "ExpressionType": 0,
      "DollPositionType": 0,
      "AnimationType": 0,
      "SubCutsceneType": 0,
      "NotificationType": 0,
      "GirlPairRelationshipType": 0,
      "SpecialStepPrefabName": null,
      "BannerTextPrefabName": null,
      "WindowPrefabName": null,
      "EmitterBehaviorName": null,
      "StringValue": "",
      "FloatValue": 0.0,
      "ProceedFloat": 0.0,
      "TargetGirlDefinitionID": 4,
      "IntValue": 0,
      "EaseType": 0,
      "EditorSelectedBranchIndex": 0,
      "DialogTriggerDefinitionID": -1,
      "EditorSelectedOptionIndex": 0,
      "GirlDefinitionID": -1,
      "ExpressionIndex": 0,
      "HairstyleIndex": 0,
      "OutfitIndex": 0,
      "SubCutsceneDefinitionID": -1,
      "SkipStep": false,
      "TargetAlt": false,
      "BoolValue": false,
      "SetMood": false,
      "ProceedBool": false,
      "PositionInfo": {
        "Xpos": 0.0,
        "Ypos": 0.0
      },
      "AudioKlipInfo": {
        "AudioClipInfo": null,
        "Volume": 1.0
      },
      "LogicActionInfo": {
        "Type": 0,
        "AffectionType": 0,
        "ResourceType": 0,
        "PuzzleState": 0,
        "StringValue": "",
        "FloatValue": 0.0,
        "IntValue": 0,
        "LocationDefinitionID": -1,
        "GirlPairDefinitionID": -1,
        "CutsceneDefinitionID": -1,
        "ItemDefinitionID": -1,
        "GirlDefinitionID": -1,
        "BoolValue": false,
        "BackgroundMusic": {
          "AudioClipInfo": null,
          "Volume": 1.0
        }
      },
      "DialogLineInfo": {
        "DialogText": "I'm very sorry you had to deal with that.▸▸▸▸▸ You have a▸▸ good heart...▸▸▸▸▸ and great nails.",
        "YuriDialogText": "",
        "Yuri": false,
        "YuriAudioClipInfo": null,
        "AudioClipInfo": {
          "Path": "vo_attr_zoey_polly_7_zoey",
          "IsExternal": false
        },
        "StartExpression": {
          "expressionType": 2,
          "eyesClosed": false,
          "percentRead": 0.0
        },
        "EndExpression": {
          "expressionType": 0,
          "eyesClosed": false,
          "percentRead": 0.0
        },
        "Expressions": [
          {
            "expressionType": 0,
            "eyesClosed": false,
            "percentRead": 0.781818151
          }
        ]
      },
      "DialogOptionInfos": [],
      "BranchInfos": []
    },
    {
      "StepType": 5,
      "ProceedType": 0,
      "DollTargetType": 0,
      "TargetDollOrientation": 0,
      "ExpressionType": 0,
      "DollPositionType": 0,
      "AnimationType": 0,
      "SubCutsceneType": 0,
      "NotificationType": 0,
      "GirlPairRelationshipType": 0,
      "SpecialStepPrefabName": null,
      "BannerTextPrefabName": null,
      "WindowPrefabName": null,
      "EmitterBehaviorName": null,
      "StringValue": "",
      "FloatValue": 0.0,
      "ProceedFloat": 0.0,
      "TargetGirlDefinitionID": 12,
      "IntValue": 0,
      "EaseType": 0,
      "EditorSelectedBranchIndex": 0,
      "DialogTriggerDefinitionID": -1,
      "EditorSelectedOptionIndex": 0,
      "GirlDefinitionID": -1,
      "ExpressionIndex": 0,
      "HairstyleIndex": 0,
      "OutfitIndex": 0,
      "SubCutsceneDefinitionID": -1,
      "SkipStep": false,
      "TargetAlt": false,
      "BoolValue": false,
      "SetMood": false,
      "ProceedBool": true,
      "PositionInfo": {
        "Xpos": 0.0,
        "Ypos": 0.0
      },
      "AudioKlipInfo": {
        "AudioClipInfo": null,
        "Volume": 1.0
      },
      "LogicActionInfo": {
        "Type": 0,
        "AffectionType": 0,
        "ResourceType": 0,
        "PuzzleState": 0,
        "StringValue": "",
        "FloatValue": 0.0,
        "IntValue": 0,
        "LocationDefinitionID": -1,
        "GirlPairDefinitionID": -1,
        "CutsceneDefinitionID": -1,
        "ItemDefinitionID": -1,
        "GirlDefinitionID": -1,
        "BoolValue": false,
        "BackgroundMusic": {
          "AudioClipInfo": null,
          "Volume": 1.0
        }
      },
      "DialogLineInfo": {
        "DialogText": "[heh]▸▸[hh]▸▸▸Awww,▸▸ thanks Zoey,▸▸▸ that means a lot.▸▸▸▸▸▸▸▸ YOU have a good heart...▸▸▸▸▸▸▸▸ and you know what?▸▸ GREAT▸▸ makeup▸▸ too!",
        "YuriDialogText": "",
        "Yuri": false,
        "YuriAudioClipInfo": null,
        "AudioClipInfo": {
          "Path": "vo_attr_zoey_polly_8_polly",
          "IsExternal": false
        },
        "StartExpression": {
          "expressionType": 3,
          "eyesClosed": false,
          "percentRead": 0.0
        },
        "EndExpression": {
          "expressionType": 0,
          "eyesClosed": false,
          "percentRead": 0.0
        },
        "Expressions": [
          {
            "expressionType": 2,
            "eyesClosed": false,
            "percentRead": 0.118181825
          },
          {
            "expressionType": 7,
            "eyesClosed": false,
            "percentRead": 0.436363637
          },
          {
            "expressionType": 4,
            "eyesClosed": false,
            "percentRead": 0.6636363
          },
          {
            "expressionType": 0,
            "eyesClosed": false,
            "percentRead": 0.8272728
          }
        ]
      },
      "DialogOptionInfos": [],
      "BranchInfos": []
    }
  ],
  "IsAdditive": false,
  "Id": 49
}