{
  "LocationName": "Hotel Lobby",
  "LocationType": 0,
  "BgMusic": {
    "AudioClipInfo": {
      "Path": "bgm_hotel_lobby",
      "IsExternal": false
    },
    "Volume": 0.5
  },
  "BgYOffset": 220.0,
  "FinderLocationIcon": {
    "Path": "ui_location_icon_lobby",
    "IsExternal": false
  },
  "DateGirlStyleType": 0,
  "NonStopOptionText": "",
  "SpecialLabels": [],
  "Backgrounds": [
    {
      "Path": "loc_bg_sim_lobby_0",
      "IsExternal": false
    },
    {
      "Path": "loc_bg_sim_lobby_1",
      "IsExternal": false
    },
    {
      "Path": "loc_bg_sim_lobby_2",
      "IsExternal": false
    },
    {
      "Path": "loc_bg_sim_lobby_3",
      "IsExternal": false
    }
  ],
  "ArriveBundleList": [],
  "DepartBundleList": [],
  "IsAdditive": false,
  "Id": 7
}