{
  "LocationName": "Boardwalk",
  "LocationType": 0,
  "BgMusic": {
    "AudioClipInfo": {
      "Path": "bgm_boardwalk",
      "IsExternal": false
    },
    "Volume": 0.5
  },
  "BgYOffset": 80.0,
  "FinderLocationIcon": {
    "Path": "ui_location_icon_boardwalk",
    "IsExternal": false
  },
  "DateGirlStyleType": 0,
  "NonStopOptionText": "",
  "SpecialLabels": [],
  "Backgrounds": [
    {
      "Path": "loc_bg_sim_boardwalk_0",
      "IsExternal": false
    },
    {
      "Path": "loc_bg_sim_boardwalk_1",
      "IsExternal": false
    },
    {
      "Path": "loc_bg_sim_boardwalk_2",
      "IsExternal": false
    },
    {
      "Path": "loc_bg_sim_boardwalk_3",
      "IsExternal": false
    }
  ],
  "ArriveBundleList": [],
  "DepartBundleList": [],
  "IsAdditive": false,
  "Id": 2
}