{
  "BurstSprites": [
    {
      "Path": "particle_token_energy_burst_talent",
      "IsExternal": false
    }
  ],
  "TrailSprites": [
    {
      "Path": "particle_token_energy_talent",
      "IsExternal": false
    },
    {
      "Path": "particle_token_energy_mist_talent",
      "IsExternal": false
    }
  ],
  "SplashSprites": [
    {
      "Path": "particle_token_energy_talent",
      "IsExternal": false
    },
    {
      "Path": "particle_token_energy_mist_talent",
      "IsExternal": false
    }
  ],
  "SurgeSprites": [
    {
      "Path": "particle_token_energy_talent",
      "IsExternal": false
    }
  ],
  "TextMaterialName": "stm_talent",
  "TextColorInfo": {
    "R": 0.6313726,
    "G": 0.819607854,
    "B": 0.9607843,
    "A": 1.0
  },
  "OutlineColorInfo": {
    "R": 0.08235294,
    "G": 0.407843143,
    "B": 0.6901961,
    "A": 1.0
  },
  "ShadowColorInfo": {
    "R": 0.08235294,
    "G": 0.407843143,
    "B": 0.6901961,
    "A": 1.0
  },
  "SurgeColorInfo": {
    "R": 0.08235294,
    "G": 0.407843143,
    "B": 0.6901961,
    "A": 1.0
  },
  "SurgeExpression": 3,
  "SurgeEyesClosed": false,
  "NegSurgeExpression": 4,
  "NegSurgeEyesClosed": false,
  "BossSurgeExpression": 1,
  "BossSurgeEyesClosed": false,
  "IsAdditive": false,
  "Id": 1
}